LICENSE.txt
README.md
setup.py
SimpleGooglePing/SimpleGooglePing.py
SimpleGooglePing.egg-info/PKG-INFO
SimpleGooglePing.egg-info/SOURCES.txt
SimpleGooglePing.egg-info/dependency_links.txt
SimpleGooglePing.egg-info/top_level.txt